LICENSE
MANIFEST.in
README.md
requirements.txt
setup.py
llm_analyst/__init__.py
llm_analyst/chat_models/__init__.py
llm_analyst/chat_models/groq.py
llm_analyst/chat_models/openai.py
llm_analyst/core/__init__.py
llm_analyst/core/config.py
llm_analyst/core/exceptions.py
llm_analyst/core/prompts.py
llm_analyst/core/research_analyst.py
llm_analyst/core/research_editor.py
llm_analyst/core/research_publisher.py
llm_analyst/core/research_state.py
llm_analyst/core/research_writer.py
llm_analyst/documents/__init__.py
llm_analyst/documents/document.py
llm_analyst/documents/vector_store.py
llm_analyst/embedding_methods/__init__.py
llm_analyst/embedding_methods/compressor.py
llm_analyst/resources/__init__.py
llm_analyst/resources/llm_analyst.config
llm_analyst/resources/pdf_styles.css
llm_analyst/resources/prompts.json
llm_analyst/scrapers/__init__.py
llm_analyst/scrapers/scraper_methods.py
llm_analyst/search_methods/__init__.py
llm_analyst/search_methods/internet_search.py
llm_analyst/utils/__init__.py
llm_analyst/utils/app_logging.py
llm_analyst/utils/utilities.py
research_task.egg-info/PKG-INFO
research_task.egg-info/SOURCES.txt
research_task.egg-info/dependency_links.txt
research_task.egg-info/not-zip-safe
research_task.egg-info/requires.txt
research_task.egg-info/top_level.txt